{
  "id": "697b26f6-20d9-43ad-b4cc-07200d4286a6",
  "name": "Untitled document",
  "description": "Crafting Dialogues that Drive Business Success. (Converted from Langflow Store for AxieStudio compatibility)",
  "type": "FLOW",
  "is_component": false,
  "author": {
    "username": "cxfxcxb",
    "first_name": "Christopher Frederick Che",
    "last_name": "Bösch",
    "id": "a290c466-4d85-4ecf-be58-9300a907923c",
    "full_name": "Christopher Frederick Che Bösch"
  },
  "store_url": "https://www.langflow.store/store/component/697b26f6-20d9-43ad-b4cc-07200d4286a6",
  "stats": {
    "downloads": 0,
    "likes": 0
  },
  "dates": {
    "created": "2024-06-03T14:50:03.016Z",
    "updated": "2024-06-03T14:50:03.064Z",
    "downloaded": "2025-08-19T17:50:05.485Z"
  },
  "tags": [
    {
      "tags_id": {
        "name": "Vector Store",
        "id": "cd614b49-dd57-4c8b-a5eb-f8bb5f957b9a"
      }
    }
  ],
  "technical": {
    "last_tested_version": "0.6.17",
    "private": false,
    "status": "Public"
  },
  "data": {
    "nodes": [],
    "edges": [],
    "viewport": {
      "x": 0,
      "y": 0,
      "zoom": 1
    }
  },
  "metadata": {
    "total": 0
  },
  "original": {
    "id": "697b26f6-20d9-43ad-b4cc-07200d4286a6",
    "name": "Untitled document",
    "description": "Crafting Dialogues that Drive Business Success.",
    "is_component": false,
    "liked_by_count": "2",
    "downloads_count": "10",
    "metadata": {
      "total": 0
    },
    "last_tested_version": "0.6.17",
    "private": false,
    "data": {
      "nodes": [],
      "edges": [],
      "viewport": {
        "x": 0,
        "y": 0,
        "zoom": 1
      }
    },
    "date_created": "2024-06-03T14:50:03.016Z",
    "date_updated": "2024-06-03T14:50:03.064Z",
    "status": "Public",
    "sort": null,
    "user_updated": "a290c466-4d85-4ecf-be58-9300a907923c",
    "user_created": {
      "username": "cxfxcxb",
      "first_name": "Christopher Frederick Che",
      "last_name": "Bösch",
      "id": "a290c466-4d85-4ecf-be58-9300a907923c"
    },
    "tags": [
      {
        "tags_id": {
          "name": "Vector Store",
          "id": "cd614b49-dd57-4c8b-a5eb-f8bb5f957b9a"
        }
      }
    ]
  },
  "conversion": {
    "converted_at": "2025-08-19T18:08:59.439Z",
    "converted_from": "langflow",
    "converted_to": "axiestudio",
    "conversions_made": 0,
    "converter_version": "1.0.0"
  }
}